<bill session="116" type="h" number="8147" updated="2020-09-15T07:15:17Z">
  <state datetime="2020-09-01">REFERRED</state>
  <status>
    <introduced datetime="2020-09-01"/>
  </status>
  <introduced datetime="2020-09-01"/>
  <titles>
    <title type="short" as="introduced">Testing, Researching, and Expanding Alternative Treatments Act</title>
    <title type="short" as="introduced">Testing, Researching, and Expanding Alternative Treatments Act</title>
    <title type="short" as="introduced">TREAT Act</title>
    <title type="short" as="introduced">TREAT Act</title>
    <title type="display">TREAT Act</title>
    <title type="official" as="introduced">To direct the Secretary of Veterans Affairs to expand an existing pilot program, and to establish a new pilot program, related to complementary and integrative health services for veterans.</title>
  </titles>
  <sponsor bioguide_id="L000588"/>
  <cosponsors>
    <cosponsor bioguide_id="F000466" joined="2020-09-01"/>
    <cosponsor bioguide_id="R000610" joined="2020-09-04"/>
  </cosponsors>
  <actions>
    <action datetime="2020-09-01">
      <text>Introduced in House</text>
    </action>
    <action datetime="2020-09-01" state="REFERRED">
      <text>Referred to the House Committee on Veterans' Affairs.</text>
    </action>
    <action datetime="2020-09-10">
      <text>Committee Hearings Held.</text>
    </action>
  </actions>
  <committees>
    <committee subcommittee="" code="HSVR" name="House Veterans' Affairs" activity="Hearings, Referral"/>
  </committees>
  <relatedbills/>
  <subjects>
    <term name="Armed forces and national security"/>
    <term name="Alternative treatments"/>
    <term name="Animal protection and human-animal relationships"/>
    <term name="Congressional oversight"/>
    <term name="Government studies and investigations"/>
    <term name="Health care quality"/>
    <term name="Health information and medical records"/>
    <term name="Higher education"/>
    <term name="Mammals"/>
    <term name="Medical research"/>
    <term name="Mental health"/>
    <term name="Outdoor recreation"/>
    <term name="Veterans' medical care"/>
  </subjects>
  <amendments/>
  <committee-reports/>
</bill>
