<?xml version="1.0" encoding="UTF-8"?>
<billStatus>
  <bill>
    <billNumber>3563</billNumber>
    <createDate>2019-06-28T07:12:16Z</createDate>
    <updateDate>2020-09-18T07:15:52Z</updateDate>
    <originChamber>House</originChamber>
    <billType>HR</billType>
    <introducedDate>2019-06-27</introducedDate>
    <congress>116</congress>
    <constitutionalAuthorityStatementText><![CDATA[<pre>[Congressional Record Volume 165, Number 109 (Thursday, June 27, 2019)][House]From the Congressional Record Online through the Government Publishing Office [<a href="http://www.gpo.gov">www.gpo.gov</a>]By Ms. GARCIA of Texas:H.R. 3563.Congress has the power to enact this legislation pursuantto the following:This bill is enacted pursuant to the power granted toCongress under Article I, Section 8, Clause 3 of the UnitedStates Constitution.[Page H5259]</pre>]]></constitutionalAuthorityStatementText>
    <recordedVotes />
    <committees>
      <billCommittees>
        <item>
          <systemCode>hsju00</systemCode>
          <name>Judiciary Committee</name>
          <chamber>House</chamber>
          <type>Standing</type>
          <subcommittees>
            <item>
              <systemCode>hsju08</systemCode>
              <name>Crime, Terrorism, and Homeland Security Subcommittee</name>
              <activities>
                <item>
                  <name>Referred to</name>
                  <date>2019-07-30T19:47:44Z</date>
                </item>
              </activities>
            </item>
          </subcommittees>
          <activities>
            <item>
              <name>Referred to</name>
              <date>2019-06-27T13:06:20Z</date>
            </item>
          </activities>
        </item>
      </billCommittees>
    </committees>
    <committeeReports />
    <relatedBills>
      <item>
        <latestTitle>Stop Shackling and Detaining Pregnant Women Act</latestTitle>
        <congress>116</congress>
        <number>648</number>
        <type>S</type>
        <latestAction>
          <actionDate>2019-03-05</actionDate>
          <text>Read twice and referred to the Committee on the Judiciary.</text>
        </latestAction>
        <relationshipDetails>
          <item>
            <type>Identical bill</type>
            <identifiedBy>CRS</identifiedBy>
          </item>
        </relationshipDetails>
      </item>
    </relatedBills>
    <actions>
      <item>
        <actionDate>2019-07-30</actionDate>
        <committees>
          <item>
            <systemCode>hsju08</systemCode>
            <name>Crime, Terrorism, and Homeland Security Subcommittee</name>
          </item>
        </committees>
        <links />
        <sourceSystem>
          <code>1</code>
          <name>House committee actions</name>
        </sourceSystem>
        <text>Referred to the Subcommittee on Crime, Terrorism, and Homeland Security.</text>
        <type>Committee</type>
      </item>
      <item>
        <actionDate>2019-06-27</actionDate>
        <links />
        <text>Referred to the House Committee on the Judiciary.</text>
        <type>IntroReferral</type>
        <actionCode>H11100</actionCode>
        <sourceSystem>
          <code>2</code>
          <name>House floor actions</name>
        </sourceSystem>
        <committees>
          <item>
            <systemCode>hsju00</systemCode>
            <name>Judiciary Committee</name>
          </item>
        </committees>
      </item>
      <item>
        <actionDate>2019-06-27</actionDate>
        <links />
        <text>Introduced in House</text>
        <type>IntroReferral</type>
        <actionCode>Intro-H</actionCode>
        <sourceSystem>
          <code>9</code>
          <name>Library of Congress</name>
        </sourceSystem>
        <committees />
      </item>
      <item>
        <actionDate>2019-06-27</actionDate>
        <links />
        <text>Introduced in House</text>
        <type>IntroReferral</type>
        <actionCode>1000</actionCode>
        <sourceSystem>
          <code>9</code>
          <name>Library of Congress</name>
        </sourceSystem>
        <committees />
      </item>
      <actionTypeCounts>
        <placeholderTextForH>1</placeholderTextForH>
        <billReferrals>1</billReferrals>
        <introducedInTheHouse>1</introducedInTheHouse>
        <introducedInHouse>1</introducedInHouse>
      </actionTypeCounts>
      <actionByCounts>
        <houseOfRepresentatives>4</houseOfRepresentatives>
      </actionByCounts>
    </actions>
    <sponsors>
      <item>
        <bioguideId>G000587</bioguideId>
        <fullName>Rep. Garcia, Sylvia R. [D-TX-29]</fullName>
        <firstName>Sylvia</firstName>
        <middleName>R.</middleName>
        <lastName>Garcia</lastName>
        <party>D</party>
        <state>TX</state>
        <identifiers>
          <lisID>2450</lisID>
          <bioguideId>G000587</bioguideId>
          <gpoId />
        </identifiers>
        <district>29</district>
        <byRequestType />
      </item>
    </sponsors>
    <cosponsors>
      <item>
        <bioguideId>M000087</bioguideId>
        <fullName>Rep. Maloney, Carolyn B. [D-NY-12]</fullName>
        <firstName>CAROLYN</firstName>
        <middleName>B.</middleName>
        <lastName>MALONEY</lastName>
        <party>D</party>
        <state>NY</state>
        <identifiers>
          <lisID>729</lisID>
          <bioguideId>M000087</bioguideId>
          <gpoId>8075</gpoId>
        </identifiers>
        <district>12</district>
        <sponsorshipDate>2019-06-27</sponsorshipDate>
        <isOriginalCosponsor>True</isOriginalCosponsor>
        <sponsorshipWithdrawnDate />
      </item>
      <item>
        <bioguideId>N000147</bioguideId>
        <fullName>Rep. Norton, Eleanor Holmes [D-DC-At Large]</fullName>
        <firstName>ELEANOR</firstName>
        <middleName>HOLMES</middleName>
        <lastName>NORTON</lastName>
        <party>D</party>
        <state>DC</state>
        <identifiers>
          <lisID>868</lisID>
          <bioguideId>N000147</bioguideId>
          <gpoId>7871</gpoId>
        </identifiers>
        <district>0</district>
        <sponsorshipDate>2019-06-27</sponsorshipDate>
        <isOriginalCosponsor>True</isOriginalCosponsor>
        <sponsorshipWithdrawnDate />
      </item>
      <item>
        <bioguideId>E000297</bioguideId>
        <fullName>Rep. Espaillat, Adriano [D-NY-13]</fullName>
        <firstName>Adriano</firstName>
        <middleName />
        <lastName>Espaillat</lastName>
        <party>D</party>
        <state>NY</state>
        <identifiers>
          <lisID>2342</lisID>
          <bioguideId>E000297</bioguideId>
          <gpoId />
        </identifiers>
        <district>13</district>
        <sponsorshipDate>2019-06-27</sponsorshipDate>
        <isOriginalCosponsor>True</isOriginalCosponsor>
        <sponsorshipWithdrawnDate />
      </item>
      <item>
        <bioguideId>K000368</bioguideId>
        <fullName>Rep. Kirkpatrick, Ann [D-AZ-2]</fullName>
        <firstName>Ann</firstName>
        <middleName />
        <lastName>Kirkpatrick</lastName>
        <party>D</party>
        <state>AZ</state>
        <identifiers>
          <lisID>1907</lisID>
          <bioguideId>K000368</bioguideId>
          <gpoId>7220</gpoId>
        </identifiers>
        <district>2</district>
        <sponsorshipDate>2019-06-27</sponsorshipDate>
        <isOriginalCosponsor>True</isOriginalCosponsor>
        <sponsorshipWithdrawnDate />
      </item>
      <item>
        <bioguideId>C001072</bioguideId>
        <fullName>Rep. Carson, Andre [D-IN-7]</fullName>
        <firstName>Andre</firstName>
        <middleName />
        <lastName>Carson</lastName>
        <party>D</party>
        <state>IN</state>
        <identifiers>
          <lisID>1889</lisID>
          <bioguideId>C001072</bioguideId>
          <gpoId>7946</gpoId>
        </identifiers>
        <district>7</district>
        <sponsorshipDate>2019-06-27</sponsorshipDate>
        <isOriginalCosponsor>True</isOriginalCosponsor>
        <sponsorshipWithdrawnDate />
      </item>
      <item>
        <bioguideId>G000551</bioguideId>
        <fullName>Rep. Grijalva, Raul M. [D-AZ-3]</fullName>
        <firstName>Raul</firstName>
        <middleName>M.</middleName>
        <lastName>Grijalva</lastName>
        <party>D</party>
        <state>AZ</state>
        <identifiers>
          <lisID>1708</lisID>
          <bioguideId>G000551</bioguideId>
          <gpoId>7804</gpoId>
        </identifiers>
        <district>3</district>
        <sponsorshipDate>2019-06-27</sponsorshipDate>
        <isOriginalCosponsor>True</isOriginalCosponsor>
        <sponsorshipWithdrawnDate />
      </item>
      <item>
        <bioguideId>E000299</bioguideId>
        <fullName>Rep. Escobar, Veronica [D-TX-16]</fullName>
        <firstName>Veronica</firstName>
        <middleName />
        <lastName>Escobar</lastName>
        <party>D</party>
        <state>TX</state>
        <identifiers>
          <lisID>2448</lisID>
          <bioguideId>E000299</bioguideId>
          <gpoId />
        </identifiers>
        <district>16</district>
        <sponsorshipDate>2019-06-27</sponsorshipDate>
        <isOriginalCosponsor>True</isOriginalCosponsor>
        <sponsorshipWithdrawnDate />
      </item>
      <item>
        <bioguideId>C001097</bioguideId>
        <fullName>Rep. Cardenas, Tony [D-CA-29]</fullName>
        <firstName>Tony</firstName>
        <middleName />
        <lastName>Cardenas</lastName>
        <party>D</party>
        <state>CA</state>
        <identifiers>
          <lisID>2107</lisID>
          <bioguideId>C001097</bioguideId>
          <gpoId />
        </identifiers>
        <district>29</district>
        <sponsorshipDate>2019-06-27</sponsorshipDate>
        <isOriginalCosponsor>True</isOriginalCosponsor>
        <sponsorshipWithdrawnDate />
      </item>
      <item>
        <bioguideId>V000130</bioguideId>
        <fullName>Rep. Vargas, Juan [D-CA-51]</fullName>
        <firstName>Juan</firstName>
        <middleName />
        <lastName>Vargas</lastName>
        <party>D</party>
        <state>CA</state>
        <identifiers>
          <lisID>2112</lisID>
          <bioguideId>V000130</bioguideId>
          <gpoId />
        </identifiers>
        <district>51</district>
        <sponsorshipDate>2019-06-27</sponsorshipDate>
        <isOriginalCosponsor>True</isOriginalCosponsor>
        <sponsorshipWithdrawnDate />
      </item>
      <item>
        <bioguideId>S001206</bioguideId>
        <fullName>Rep. Shalala, Donna E. [D-FL-27]</fullName>
        <firstName>Donna</firstName>
        <middleName>E.</middleName>
        <lastName>Shalala</lastName>
        <party>D</party>
        <state>FL</state>
        <identifiers>
          <lisID>2391</lisID>
          <bioguideId>S001206</bioguideId>
          <gpoId />
        </identifiers>
        <district>27</district>
        <sponsorshipDate>2019-06-27</sponsorshipDate>
        <isOriginalCosponsor>True</isOriginalCosponsor>
        <sponsorshipWithdrawnDate />
      </item>
      <item>
        <bioguideId>S001145</bioguideId>
        <fullName>Rep. Schakowsky, Janice D. [D-IL-9]</fullName>
        <firstName>JANICE</firstName>
        <middleName>D.</middleName>
        <lastName>SCHAKOWSKY</lastName>
        <party>D</party>
        <state>IL</state>
        <identifiers>
          <lisID>1588</lisID>
          <bioguideId>S001145</bioguideId>
          <gpoId>7929</gpoId>
        </identifiers>
        <district>9</district>
        <sponsorshipDate>2019-06-27</sponsorshipDate>
        <isOriginalCosponsor>True</isOriginalCosponsor>
        <sponsorshipWithdrawnDate />
      </item>
      <item>
        <bioguideId>W000797</bioguideId>
        <fullName>Rep. Wasserman Schultz, Debbie [D-FL-23]</fullName>
        <firstName>Debbie</firstName>
        <middleName />
        <lastName>Wasserman Schultz</lastName>
        <party>D</party>
        <state>FL</state>
        <identifiers>
          <lisID>1777</lisID>
          <bioguideId>W000797</bioguideId>
          <gpoId>7892</gpoId>
        </identifiers>
        <district>23</district>
        <sponsorshipDate>2019-06-27</sponsorshipDate>
        <isOriginalCosponsor>True</isOriginalCosponsor>
        <sponsorshipWithdrawnDate />
      </item>
      <item>
        <bioguideId>B000574</bioguideId>
        <fullName>Rep. Blumenauer, Earl [D-OR-3]</fullName>
        <firstName>EARL</firstName>
        <middleName />
        <lastName>BLUMENAUER</lastName>
        <party>D</party>
        <state>OR</state>
        <identifiers>
          <lisID>99</lisID>
          <bioguideId>B000574</bioguideId>
          <gpoId>8116</gpoId>
        </identifiers>
        <district>3</district>
        <sponsorshipDate>2019-06-27</sponsorshipDate>
        <isOriginalCosponsor>True</isOriginalCosponsor>
        <sponsorshipWithdrawnDate />
      </item>
      <item>
        <bioguideId>K000009</bioguideId>
        <fullName>Rep. Kaptur, Marcy [D-OH-9]</fullName>
        <firstName>MARCY</firstName>
        <middleName />
        <lastName>KAPTUR</lastName>
        <party>D</party>
        <state>OH</state>
        <identifiers>
          <lisID>616</lisID>
          <bioguideId>K000009</bioguideId>
          <gpoId>8099</gpoId>
        </identifiers>
        <district>9</district>
        <sponsorshipDate>2019-06-27</sponsorshipDate>
        <isOriginalCosponsor>True</isOriginalCosponsor>
        <sponsorshipWithdrawnDate />
      </item>
      <item>
        <bioguideId>N000179</bioguideId>
        <fullName>Rep. Napolitano, Grace F. [D-CA-32]</fullName>
        <firstName>GRACE</firstName>
        <middleName>F.</middleName>
        <lastName>NAPOLITANO</lastName>
        <party>D</party>
        <state>CA</state>
        <identifiers>
          <lisID>1602</lisID>
          <bioguideId>N000179</bioguideId>
          <gpoId>7843</gpoId>
        </identifiers>
        <district>32</district>
        <sponsorshipDate>2019-06-27</sponsorshipDate>
        <isOriginalCosponsor>True</isOriginalCosponsor>
        <sponsorshipWithdrawnDate />
      </item>
      <item>
        <bioguideId>J000288</bioguideId>
        <fullName>Rep. Johnson, Henry C. "Hank," Jr. [D-GA-4]</fullName>
        <firstName>Henry</firstName>
        <middleName>C. "Hank"</middleName>
        <lastName>Johnson</lastName>
        <party>D</party>
        <state>GA</state>
        <identifiers>
          <lisID>1843</lisID>
          <bioguideId>J000288</bioguideId>
          <gpoId>7901</gpoId>
        </identifiers>
        <district>4</district>
        <sponsorshipDate>2019-06-27</sponsorshipDate>
        <isOriginalCosponsor>True</isOriginalCosponsor>
        <sponsorshipWithdrawnDate />
      </item>
      <item>
        <bioguideId>M001160</bioguideId>
        <fullName>Rep. Moore, Gwen [D-WI-4]</fullName>
        <firstName>Gwen</firstName>
        <middleName />
        <lastName>Moore</lastName>
        <party>D</party>
        <state>WI</state>
        <identifiers>
          <lisID>1811</lisID>
          <bioguideId>M001160</bioguideId>
          <gpoId>8217</gpoId>
        </identifiers>
        <district>4</district>
        <sponsorshipDate>2019-06-27</sponsorshipDate>
        <isOriginalCosponsor>True</isOriginalCosponsor>
        <sponsorshipWithdrawnDate />
      </item>
      <item>
        <bioguideId>R000515</bioguideId>
        <fullName>Rep. Rush, Bobby L. [D-IL-1]</fullName>
        <firstName>BOBBY</firstName>
        <middleName>L.</middleName>
        <lastName>RUSH</lastName>
        <party>D</party>
        <state>IL</state>
        <identifiers>
          <lisID>1003</lisID>
          <bioguideId>R000515</bioguideId>
          <gpoId>7921</gpoId>
        </identifiers>
        <district>1</district>
        <sponsorshipDate>2019-06-27</sponsorshipDate>
        <isOriginalCosponsor>True</isOriginalCosponsor>
        <sponsorshipWithdrawnDate />
      </item>
      <item>
        <bioguideId>A000370</bioguideId>
        <fullName>Rep. Adams, Alma S. [D-NC-12]</fullName>
        <firstName>Alma</firstName>
        <middleName>S.</middleName>
        <lastName>Adams</lastName>
        <party>D</party>
        <state>NC</state>
        <identifiers>
          <lisID>2201</lisID>
          <bioguideId>A000370</bioguideId>
          <gpoId />
        </identifiers>
        <district>12</district>
        <sponsorshipDate>2019-06-27</sponsorshipDate>
        <isOriginalCosponsor>True</isOriginalCosponsor>
        <sponsorshipWithdrawnDate />
      </item>
      <item>
        <bioguideId>T000481</bioguideId>
        <fullName>Rep. Tlaib, Rashida [D-MI-13]</fullName>
        <firstName>Rashida</firstName>
        <middleName />
        <lastName>Tlaib</lastName>
        <party>D</party>
        <state>MI</state>
        <identifiers>
          <lisID>2410</lisID>
          <bioguideId>T000481</bioguideId>
          <gpoId />
        </identifiers>
        <district>13</district>
        <sponsorshipDate>2019-06-27</sponsorshipDate>
        <isOriginalCosponsor>True</isOriginalCosponsor>
        <sponsorshipWithdrawnDate />
      </item>
      <item>
        <bioguideId>M001188</bioguideId>
        <fullName>Rep. Meng, Grace [D-NY-6]</fullName>
        <firstName>Grace</firstName>
        <middleName />
        <lastName>Meng</lastName>
        <party>D</party>
        <state>NY</state>
        <identifiers>
          <lisID>2148</lisID>
          <bioguideId>M001188</bioguideId>
          <gpoId />
        </identifiers>
        <district>6</district>
        <sponsorshipDate>2019-06-27</sponsorshipDate>
        <isOriginalCosponsor>True</isOriginalCosponsor>
        <sponsorshipWithdrawnDate />
      </item>
      <item>
        <bioguideId>G000586</bioguideId>
        <fullName>Rep. Garcia, Jesus G. "Chuy" [D-IL-4]</fullName>
        <firstName>Jesus</firstName>
        <middleName>G.</middleName>
        <lastName>Garcia</lastName>
        <party>D</party>
        <state>IL</state>
        <identifiers>
          <lisID>2397</lisID>
          <bioguideId>G000586</bioguideId>
          <gpoId />
        </identifiers>
        <district>4</district>
        <sponsorshipDate>2019-06-27</sponsorshipDate>
        <isOriginalCosponsor>True</isOriginalCosponsor>
        <sponsorshipWithdrawnDate />
      </item>
      <item>
        <bioguideId>G000581</bioguideId>
        <fullName>Rep. Gonzalez, Vicente [D-TX-15]</fullName>
        <firstName>Vicente</firstName>
        <middleName />
        <lastName>Gonzalez</lastName>
        <party>D</party>
        <state>TX</state>
        <identifiers>
          <lisID>2349</lisID>
          <bioguideId>G000581</bioguideId>
          <gpoId />
        </identifiers>
        <district>15</district>
        <sponsorshipDate>2019-06-27</sponsorshipDate>
        <isOriginalCosponsor>True</isOriginalCosponsor>
        <sponsorshipWithdrawnDate />
      </item>
      <item>
        <bioguideId>N000002</bioguideId>
        <fullName>Rep. Nadler, Jerrold [D-NY-10]</fullName>
        <firstName>JERROLD</firstName>
        <middleName />
        <lastName>NADLER</lastName>
        <party>D</party>
        <state>NY</state>
        <identifiers>
          <lisID>850</lisID>
          <bioguideId>N000002</bioguideId>
          <gpoId>8069</gpoId>
        </identifiers>
        <district>10</district>
        <sponsorshipDate>2019-06-27</sponsorshipDate>
        <isOriginalCosponsor>True</isOriginalCosponsor>
        <sponsorshipWithdrawnDate />
      </item>
      <item>
        <bioguideId>M000312</bioguideId>
        <fullName>Rep. McGovern, James P. [D-MA-2]</fullName>
        <firstName>JAMES</firstName>
        <middleName>P.</middleName>
        <lastName>MCGOVERN</lastName>
        <party>D</party>
        <state>MA</state>
        <identifiers>
          <lisID>1504</lisID>
          <bioguideId>M000312</bioguideId>
          <gpoId>7968</gpoId>
        </identifiers>
        <district>2</district>
        <sponsorshipDate>2019-06-27</sponsorshipDate>
        <isOriginalCosponsor>True</isOriginalCosponsor>
        <sponsorshipWithdrawnDate />
      </item>
      <item>
        <bioguideId>D000197</bioguideId>
        <fullName>Rep. DeGette, Diana [D-CO-1]</fullName>
        <firstName>DIANA</firstName>
        <middleName />
        <lastName>DEGETTE</lastName>
        <party>D</party>
        <state>CO</state>
        <identifiers>
          <lisID>1479</lisID>
          <bioguideId>D000197</bioguideId>
          <gpoId>7859</gpoId>
        </identifiers>
        <district>1</district>
        <sponsorshipDate>2019-06-27</sponsorshipDate>
        <isOriginalCosponsor>True</isOriginalCosponsor>
        <sponsorshipWithdrawnDate />
      </item>
      <item>
        <bioguideId>D000216</bioguideId>
        <fullName>Rep. DeLauro, Rosa L. [D-CT-3]</fullName>
        <firstName>ROSA</firstName>
        <middleName />
        <lastName>DELAURO</lastName>
        <party>D</party>
        <state>CT</state>
        <identifiers>
          <lisID>281</lisID>
          <bioguideId>D000216</bioguideId>
          <gpoId>7868</gpoId>
        </identifiers>
        <district>3</district>
        <sponsorshipDate>2019-06-27</sponsorshipDate>
        <isOriginalCosponsor>True</isOriginalCosponsor>
        <sponsorshipWithdrawnDate />
      </item>
      <item>
        <bioguideId>H000324</bioguideId>
        <fullName>Rep. Hastings, Alcee L. [D-FL-20]</fullName>
        <firstName>ALCEE</firstName>
        <middleName>L.</middleName>
        <lastName>HASTINGS</lastName>
        <party>D</party>
        <state>FL</state>
        <identifiers>
          <lisID>511</lisID>
          <bioguideId>H000324</bioguideId>
          <gpoId>7895</gpoId>
        </identifiers>
        <district>20</district>
        <sponsorshipDate>2019-06-27</sponsorshipDate>
        <isOriginalCosponsor>True</isOriginalCosponsor>
        <sponsorshipWithdrawnDate />
      </item>
      <item>
        <bioguideId>H001080</bioguideId>
        <fullName>Rep. Haaland, Debra A. [D-NM-1]</fullName>
        <firstName>Debra</firstName>
        <middleName>A.</middleName>
        <lastName>Haaland</lastName>
        <party>D</party>
        <state>NM</state>
        <identifiers>
          <lisID>2423</lisID>
          <bioguideId>H001080</bioguideId>
          <gpoId />
        </identifiers>
        <district>1</district>
        <sponsorshipDate>2019-06-27</sponsorshipDate>
        <isOriginalCosponsor>True</isOriginalCosponsor>
        <sponsorshipWithdrawnDate />
      </item>
      <item>
        <bioguideId>V000081</bioguideId>
        <fullName>Rep. Velazquez, Nydia M. [D-NY-7]</fullName>
        <firstName>NYDIA</firstName>
        <middleName>M.</middleName>
        <lastName>VELAZQUEZ</lastName>
        <party>D</party>
        <state>NY</state>
        <identifiers>
          <lisID>1184</lisID>
          <bioguideId>V000081</bioguideId>
          <gpoId>8073</gpoId>
        </identifiers>
        <district>7</district>
        <sponsorshipDate>2019-06-27</sponsorshipDate>
        <isOriginalCosponsor>True</isOriginalCosponsor>
        <sponsorshipWithdrawnDate />
      </item>
      <item>
        <bioguideId>C001123</bioguideId>
        <fullName>Rep. Cisneros, Gilbert Ray, Jr. [D-CA-39]</fullName>
        <firstName>Gilbert</firstName>
        <middleName>Ray</middleName>
        <lastName>Cisneros</lastName>
        <party>D</party>
        <state>CA</state>
        <identifiers>
          <lisID>2380</lisID>
          <bioguideId>C001123</bioguideId>
          <gpoId />
        </identifiers>
        <district>39</district>
        <sponsorshipDate>2019-06-27</sponsorshipDate>
        <isOriginalCosponsor>True</isOriginalCosponsor>
        <sponsorshipWithdrawnDate />
      </item>
      <item>
        <bioguideId>P000607</bioguideId>
        <fullName>Rep. Pocan, Mark [D-WI-2]</fullName>
        <firstName>Mark</firstName>
        <middleName />
        <lastName>Pocan</lastName>
        <party>D</party>
        <state>WI</state>
        <identifiers>
          <lisID>2171</lisID>
          <bioguideId>P000607</bioguideId>
          <gpoId />
        </identifiers>
        <district>2</district>
        <sponsorshipDate>2019-06-27</sponsorshipDate>
        <isOriginalCosponsor>True</isOriginalCosponsor>
        <sponsorshipWithdrawnDate />
      </item>
      <item>
        <bioguideId>O000172</bioguideId>
        <fullName>Rep. Ocasio-Cortez, Alexandria [D-NY-14]</fullName>
        <firstName>Alexandria</firstName>
        <middleName />
        <lastName>Ocasio-Cortez</lastName>
        <party>D</party>
        <state>NY</state>
        <identifiers>
          <lisID>2427</lisID>
          <bioguideId>O000172</bioguideId>
          <gpoId />
        </identifiers>
        <district>14</district>
        <sponsorshipDate>2019-06-27</sponsorshipDate>
        <isOriginalCosponsor>True</isOriginalCosponsor>
        <sponsorshipWithdrawnDate />
      </item>
      <item>
        <bioguideId>C001124</bioguideId>
        <fullName>Rep. Cox, TJ [D-CA-21]</fullName>
        <firstName>TJ</firstName>
        <middleName />
        <lastName>Cox</lastName>
        <party>D</party>
        <state>CA</state>
        <identifiers>
          <lisID>2378</lisID>
          <bioguideId>C001124</bioguideId>
          <gpoId />
        </identifiers>
        <district>21</district>
        <sponsorshipDate>2019-07-16</sponsorshipDate>
        <isOriginalCosponsor>False</isOriginalCosponsor>
        <sponsorshipWithdrawnDate />
      </item>
      <item>
        <bioguideId>O000173</bioguideId>
        <fullName>Rep. Omar, Ilhan [D-MN-5]</fullName>
        <firstName>Ilhan</firstName>
        <middleName />
        <lastName>Omar</lastName>
        <party>D</party>
        <state>MN</state>
        <identifiers>
          <lisID>2414</lisID>
          <bioguideId>O000173</bioguideId>
          <gpoId />
        </identifiers>
        <district>5</district>
        <sponsorshipDate>2019-07-16</sponsorshipDate>
        <isOriginalCosponsor>False</isOriginalCosponsor>
        <sponsorshipWithdrawnDate />
      </item>
      <item>
        <bioguideId>M001207</bioguideId>
        <fullName>Rep. Mucarsel-Powell, Debbie [D-FL-26]</fullName>
        <firstName>Debbie</firstName>
        <middleName />
        <lastName>Mucarsel-Powell</lastName>
        <party>D</party>
        <state>FL</state>
        <identifiers>
          <lisID>2390</lisID>
          <bioguideId>M001207</bioguideId>
          <gpoId />
        </identifiers>
        <district>26</district>
        <sponsorshipDate>2019-07-16</sponsorshipDate>
        <isOriginalCosponsor>False</isOriginalCosponsor>
        <sponsorshipWithdrawnDate />
      </item>
      <item>
        <bioguideId>K000382</bioguideId>
        <fullName>Rep. Kuster, Ann M. [D-NH-2]</fullName>
        <firstName>Ann</firstName>
        <middleName>M.</middleName>
        <lastName>Kuster</lastName>
        <party>D</party>
        <state>NH</state>
        <identifiers>
          <lisID>2145</lisID>
          <bioguideId>K000382</bioguideId>
          <gpoId />
        </identifiers>
        <district>2</district>
        <sponsorshipDate>2019-07-16</sponsorshipDate>
        <isOriginalCosponsor>False</isOriginalCosponsor>
        <sponsorshipWithdrawnDate />
      </item>
      <item>
        <bioguideId>P000608</bioguideId>
        <fullName>Rep. Peters, Scott H. [D-CA-52]</fullName>
        <firstName>Scott</firstName>
        <middleName>H.</middleName>
        <lastName>Peters</lastName>
        <party>D</party>
        <state>CA</state>
        <identifiers>
          <lisID>2113</lisID>
          <bioguideId>P000608</bioguideId>
          <gpoId />
        </identifiers>
        <district>52</district>
        <sponsorshipDate>2019-07-16</sponsorshipDate>
        <isOriginalCosponsor>False</isOriginalCosponsor>
        <sponsorshipWithdrawnDate />
      </item>
      <item>
        <bioguideId>G000574</bioguideId>
        <fullName>Rep. Gallego, Ruben [D-AZ-7]</fullName>
        <firstName>Ruben</firstName>
        <middleName />
        <lastName>Gallego</lastName>
        <party>D</party>
        <state>AZ</state>
        <identifiers>
          <lisID>2226</lisID>
          <bioguideId>G000574</bioguideId>
          <gpoId />
        </identifiers>
        <district>7</district>
        <sponsorshipDate>2019-07-16</sponsorshipDate>
        <isOriginalCosponsor>False</isOriginalCosponsor>
        <sponsorshipWithdrawnDate />
      </item>
      <item>
        <bioguideId>C001066</bioguideId>
        <fullName>Rep. Castor, Kathy [D-FL-14]</fullName>
        <firstName>Kathy</firstName>
        <middleName />
        <lastName>Castor</lastName>
        <party>D</party>
        <state>FL</state>
        <identifiers>
          <lisID>1839</lisID>
          <bioguideId>C001066</bioguideId>
          <gpoId>7883</gpoId>
        </identifiers>
        <district>14</district>
        <sponsorshipDate>2019-07-16</sponsorshipDate>
        <isOriginalCosponsor>False</isOriginalCosponsor>
        <sponsorshipWithdrawnDate />
      </item>
      <item>
        <bioguideId>A000371</bioguideId>
        <fullName>Rep. Aguilar, Pete [D-CA-31]</fullName>
        <firstName>Pete</firstName>
        <middleName />
        <lastName>Aguilar</lastName>
        <party>D</party>
        <state>CA</state>
        <identifiers>
          <lisID>2229</lisID>
          <bioguideId>A000371</bioguideId>
          <gpoId />
        </identifiers>
        <district>31</district>
        <sponsorshipDate>2019-07-16</sponsorshipDate>
        <isOriginalCosponsor>False</isOriginalCosponsor>
        <sponsorshipWithdrawnDate />
      </item>
      <item>
        <bioguideId>L000586</bioguideId>
        <fullName>Rep. Lawson, Al, Jr. [D-FL-5]</fullName>
        <firstName>Al</firstName>
        <middleName />
        <lastName>Lawson</lastName>
        <party>D</party>
        <state>FL</state>
        <identifiers>
          <lisID>2317</lisID>
          <bioguideId>L000586</bioguideId>
          <gpoId />
        </identifiers>
        <district>5</district>
        <sponsorshipDate>2019-07-30</sponsorshipDate>
        <isOriginalCosponsor>False</isOriginalCosponsor>
        <sponsorshipWithdrawnDate />
      </item>
      <item>
        <bioguideId>D000627</bioguideId>
        <fullName>Rep. Demings, Val Butler [D-FL-10]</fullName>
        <firstName>Val</firstName>
        <middleName>Butler</middleName>
        <lastName>Demings</lastName>
        <party>D</party>
        <state>FL</state>
        <identifiers>
          <lisID>2320</lisID>
          <bioguideId>D000627</bioguideId>
          <gpoId />
        </identifiers>
        <district>10</district>
        <sponsorshipDate>2019-08-27</sponsorshipDate>
        <isOriginalCosponsor>False</isOriginalCosponsor>
        <sponsorshipWithdrawnDate />
      </item>
      <item>
        <bioguideId>R000606</bioguideId>
        <fullName>Rep. Raskin, Jamie [D-MD-8]</fullName>
        <firstName>Jamie</firstName>
        <middleName />
        <lastName>Raskin</lastName>
        <party>D</party>
        <state>MD</state>
        <identifiers>
          <lisID>2332</lisID>
          <bioguideId>R000606</bioguideId>
          <gpoId />
        </identifiers>
        <district>8</district>
        <sponsorshipDate>2019-08-27</sponsorshipDate>
        <isOriginalCosponsor>False</isOriginalCosponsor>
        <sponsorshipWithdrawnDate />
      </item>
      <item>
        <bioguideId>D000191</bioguideId>
        <fullName>Rep. DeFazio, Peter A. [D-OR-4]</fullName>
        <firstName>PETER</firstName>
        <middleName>A.</middleName>
        <lastName>DEFAZIO</lastName>
        <party>D</party>
        <state>OR</state>
        <identifiers>
          <lisID>279</lisID>
          <bioguideId>D000191</bioguideId>
          <gpoId>8117</gpoId>
        </identifiers>
        <district>4</district>
        <sponsorshipDate>2019-08-27</sponsorshipDate>
        <isOriginalCosponsor>False</isOriginalCosponsor>
        <sponsorshipWithdrawnDate />
      </item>
      <item>
        <bioguideId>R000486</bioguideId>
        <fullName>Rep. Roybal-Allard, Lucille [D-CA-40]</fullName>
        <firstName>LUCILLE</firstName>
        <middleName />
        <lastName>ROYBAL-ALLARD</lastName>
        <party>D</party>
        <state>CA</state>
        <identifiers>
          <lisID>997</lisID>
          <bioguideId>R000486</bioguideId>
          <gpoId>7839</gpoId>
        </identifiers>
        <district>40</district>
        <sponsorshipDate>2019-08-27</sponsorshipDate>
        <isOriginalCosponsor>False</isOriginalCosponsor>
        <sponsorshipWithdrawnDate />
      </item>
      <item>
        <bioguideId>P000617</bioguideId>
        <fullName>Rep. Pressley, Ayanna [D-MA-7]</fullName>
        <firstName>Ayanna</firstName>
        <middleName />
        <lastName>Pressley</lastName>
        <party>D</party>
        <state>MA</state>
        <identifiers>
          <lisID>2405</lisID>
          <bioguideId>P000617</bioguideId>
          <gpoId />
        </identifiers>
        <district>7</district>
        <sponsorshipDate>2019-09-12</sponsorshipDate>
        <isOriginalCosponsor>False</isOriginalCosponsor>
        <sponsorshipWithdrawnDate />
      </item>
      <item>
        <bioguideId>N000191</bioguideId>
        <fullName>Rep. Neguse, Joe [D-CO-2]</fullName>
        <firstName>Joe</firstName>
        <middleName />
        <lastName>Neguse</lastName>
        <party>D</party>
        <state>CO</state>
        <identifiers>
          <lisID>2384</lisID>
          <bioguideId>N000191</bioguideId>
          <gpoId />
        </identifiers>
        <district>2</district>
        <sponsorshipDate>2019-11-18</sponsorshipDate>
        <isOriginalCosponsor>False</isOriginalCosponsor>
        <sponsorshipWithdrawnDate />
      </item>
      <item>
        <bioguideId>K000389</bioguideId>
        <fullName>Rep. Khanna, Ro [D-CA-17]</fullName>
        <firstName>Ro</firstName>
        <middleName />
        <lastName>Khanna</lastName>
        <party>D</party>
        <state>CA</state>
        <identifiers>
          <lisID>2308</lisID>
          <bioguideId>K000389</bioguideId>
          <gpoId />
        </identifiers>
        <district>17</district>
        <sponsorshipDate>2020-04-23</sponsorshipDate>
        <isOriginalCosponsor>False</isOriginalCosponsor>
        <sponsorshipWithdrawnDate />
      </item>
      <item>
        <bioguideId>J000032</bioguideId>
        <fullName>Rep. Jackson Lee, Sheila [D-TX-18]</fullName>
        <firstName>SHEILA</firstName>
        <middleName />
        <lastName>JACKSON LEE</lastName>
        <party>D</party>
        <state>TX</state>
        <identifiers>
          <lisID>588</lisID>
          <bioguideId>J000032</bioguideId>
          <gpoId>8174</gpoId>
        </identifiers>
        <district>18</district>
        <sponsorshipDate>2020-09-17</sponsorshipDate>
        <isOriginalCosponsor>False</isOriginalCosponsor>
        <sponsorshipWithdrawnDate />
      </item>
      <item>
        <bioguideId>B001270</bioguideId>
        <fullName>Rep. Bass, Karen [D-CA-37]</fullName>
        <firstName>Karen</firstName>
        <middleName />
        <lastName>Bass</lastName>
        <party>D</party>
        <state>CA</state>
        <identifiers>
          <lisID>1996</lisID>
          <bioguideId>B001270</bioguideId>
          <gpoId>7838</gpoId>
        </identifiers>
        <district>37</district>
        <sponsorshipDate>2020-09-17</sponsorshipDate>
        <isOriginalCosponsor>False</isOriginalCosponsor>
        <sponsorshipWithdrawnDate />
      </item>
    </cosponsors>
    <cboCostEstimates />
    <laws />
    <notes />
    <policyArea>
      <name>Immigration</name>
    </policyArea>
    <subjects>
      <billSubjects>
        <legislativeSubjects>
          <item>
            <name>Abortion</name>
          </item>
          <item>
            <name>Border security and unlawful immigration</name>
          </item>
          <item>
            <name>Congressional oversight</name>
          </item>
          <item>
            <name>Department of Homeland Security</name>
          </item>
          <item>
            <name>Detention of persons</name>
          </item>
          <item>
            <name>Government information and archives</name>
          </item>
          <item>
            <name>Health care coverage and access</name>
          </item>
          <item>
            <name>Health information and medical records</name>
          </item>
          <item>
            <name>Immigration status and procedures</name>
          </item>
          <item>
            <name>Law enforcement officers</name>
          </item>
          <item>
            <name>Medical tests and diagnostic methods</name>
          </item>
          <item>
            <name>Right of privacy</name>
          </item>
          <item>
            <name>Women's health</name>
          </item>
        </legislativeSubjects>
        <policyArea>
          <name>Immigration</name>
        </policyArea>
      </billSubjects>
    </subjects>
    <summaries>
      <billSummaries>
        <item>
          <versionCode>00</versionCode>
          <actionDate>2019-06-27</actionDate>
          <actionDesc>Introduced in House</actionDesc>
          <lastSummaryUpdateDate>2019-11-15T14:00:17Z</lastSummaryUpdateDate>
          <text><![CDATA[<p><b>Stop Shackling and Detaining Pregnant Women Act</b></p> <p>This bill prohibits the Department of Homeland Security (DHS) from detaining a woman during pregnancy or postpartum recovery and must immediately release any detainee found to be pregnant, unless such woman presents an immediate and serious threat of hurting herself or others.</p> <p>A DHS detention facility may not use a restraint on a detainee who is known to be pregnant, including during labor, transport to a medical facility or birthing center, and delivery, or during postpartum recovery, except for medical or safety purposes. The bill requires DHS to use the least restrictive restraint necessary and prohibits certain specified restraint types, including four-point restraints and binding a detainee's hands behind her back.</p> <p>The bill prohibits DHS detention officers from being present during a pelvic exam of a detainee, labor, delivery, or treatment relating to a pregnancy, unless specifically requested by medical personnel. If a detention officer is requested by medical personnel, such officer shall be female, if practicable, and remain at a reasonable distance from the detainee. </p> <p>The bill requires that a pregnant detainee shall have access to health care services, including comprehensive services relating to reproductive health care and pregnancy.</p>]]></text>
          <updateDate>2019-06-27T04:00:00Z</updateDate>
          <name>Introduced in House</name>
        </item>
      </billSummaries>
    </summaries>
    <title>Stop Shackling and Detaining Pregnant Women Act</title>
    <titles>
      <item>
        <titleType>Official Title as Introduced</titleType>
        <parentTitleType />
        <title>To ensure the humane treatment of pregnant women by reinstating the presumption of release and prohibiting shackling, restraining, and other inhumane treatment of pregnant detainees, and for other purposes.</title>
        <chamberCode />
        <chamberName />
      </item>
      <item>
        <titleType>Short Titles as Introduced</titleType>
        <parentTitleType />
        <title>Stop Shackling and Detaining Pregnant Women Act</title>
        <chamberCode />
        <chamberName />
      </item>
      <item>
        <titleType>Display Title</titleType>
        <parentTitleType />
        <title>Stop Shackling and Detaining Pregnant Women Act</title>
        <chamberCode />
        <chamberName />
      </item>
      <item>
        <titleType>(Extracted from GPO) Short Titles as Introduced</titleType>
        <parentTitleType />
        <title>Stop Shackling and Detaining Pregnant Women Act</title>
        <chamberCode />
        <chamberName />
      </item>
    </titles>
    <amendments />
    <textVersions>
      <item>
        <type>Introduced in House</type>
        <date>2019-06-27T04:00:00Z</date>
        <formats>
          <item>
            <url>https://www.govinfo.gov/content/pkg/BILLS-116hr3563ih/xml/BILLS-116hr3563ih.xml</url>
          </item>
        </formats>
      </item>
    </textVersions>
    <latestAction>
      <actionDate>2019-07-30</actionDate>
      <text>Referred to the Subcommittee on Crime, Terrorism, and Homeland Security.</text>
      <links />
    </latestAction>
    <calendarNumbers />
    <version>1.0.0</version>
  </bill>
  <dublinCore xmlns:dc="http://purl.org/dc/elements/1.1/">
    <dc:format>text/xml</dc:format>
    <dc:language>EN</dc:language>
    <dc:rights>Pursuant to Title 17 Section 105 of the United States Code, this file is not subject to copyright protection and is in the public domain.</dc:rights>
    <dc:contributor>Congressional Research Service, Library of Congress</dc:contributor>
    <dc:description>This file contains bill summaries and statuses for federal legislation. A bill summary describes the most significant provisions of a piece of legislation and details the effects the legislative text may have on current law and federal programs. Bill summaries are authored by the Congressional Research Service (CRS) of the Library of Congress. As stated in Public Law 91-510 (2 USC 166 (d)(6)), one of the duties of CRS is "to prepare summaries and digests of bills and resolutions of a public general nature introduced in the Senate or House of Representatives". For more information, refer to the User Guide that accompanies this file.</dc:description>
  </dublinCore>
</billStatus>

