<bill session="116" type="h" number="5279" updated="2020-09-22T20:15:13Z">
  <state datetime="2019-12-03">REFERRED</state>
  <status>
    <introduced datetime="2019-12-03"/>
  </status>
  <introduced datetime="2019-12-03"/>
  <titles>
    <title type="short" as="introduced">Cosmetic Safety Enhancement Act of 2019</title>
    <title type="short" as="introduced">Cosmetic Safety Enhancement Act of 2019</title>
    <title type="display">Cosmetic Safety Enhancement Act of 2019</title>
    <title type="official" as="introduced">To amend the Federal Food, Drug, and Cosmetic Act to improve cosmetic safety, and for other purposes.</title>
  </titles>
  <sponsor bioguide_id="P000034"/>
  <cosponsors/>
  <actions>
    <action datetime="2019-12-03">
      <text>Introduced in House</text>
    </action>
    <action datetime="2019-12-03" state="REFERRED">
      <text>Referred to the House Committee on Energy and Commerce.</text>
    </action>
    <action datetime="2019-12-04">
      <text>Referred to the Subcommittee on Health.</text>
    </action>
    <action datetime="2020-03-11">
      <text>Subcommittee Consideration and Mark-up Session Held.</text>
    </action>
    <action datetime="2020-03-11">
      <text>Forwarded by Subcommittee to Full Committee (Amended) by Voice Vote .</text>
    </action>
  </actions>
  <committees>
    <committee subcommittee="" code="HSIF" name="House Energy and Commerce" activity="Referral"/>
    <committee subcommittee="Health" code="HSIF14" name="House Energy and Commerce" activity="Reporting, Markup, Referral"/>
  </committees>
  <relatedbills>
    <bill type="s" session="116" relation="unknown" number="726"/>
  </relatedbills>
  <subjects>
    <term name="Health"/>
    <term name="Animal protection and human-animal relationships"/>
    <term name="Business records"/>
    <term name="Congressional oversight"/>
    <term name="Consumer affairs"/>
    <term name="Cosmetics and personal care"/>
    <term name="Drug safety, medical device, and laboratory regulation"/>
    <term name="Government information and archives"/>
    <term name="Inflation and prices"/>
    <term name="Internet and video services"/>
    <term name="Licensing and registrations"/>
    <term name="Manufacturing"/>
    <term name="Performance measurement"/>
    <term name="Product safety and quality"/>
    <term name="User charges and fees"/>
  </subjects>
  <amendments/>
  <committee-reports/>
</bill>
