<?xml version="1.0" encoding="UTF-8"?>
<billStatus>
  <bill>
    <billNumber>542</billNumber>
    <createDate>2019-08-28T07:12:09Z</createDate>
    <updateDate>2020-10-20T21:16:56Z</updateDate>
    <originChamber>House</originChamber>
    <billType>HRES</billType>
    <introducedDate>2019-08-27</introducedDate>
    <congress>116</congress>
    <constitutionalAuthorityStatementText />
    <recordedVotes />
    <committees>
      <billCommittees>
        <item>
          <systemCode>hswm00</systemCode>
          <name>Ways and Means Committee</name>
          <chamber>House</chamber>
          <type>Standing</type>
          <subcommittees>
            <item>
              <systemCode>hswm03</systemCode>
              <name>Worker and Family Support Subcommittee</name>
              <activities>
                <item>
                  <name>Referred to</name>
                  <date>2019-08-27T19:37:23Z</date>
                </item>
              </activities>
            </item>
          </subcommittees>
          <activities>
            <item>
              <name>Referred to</name>
              <date>2019-08-27T18:00:12Z</date>
            </item>
          </activities>
        </item>
      </billCommittees>
    </committees>
    <committeeReports />
    <relatedBills>
      <item>
        <latestTitle>A resolution designating September 2019 as "National Kinship Care Month".</latestTitle>
        <congress>116</congress>
        <number>323</number>
        <type>SRES</type>
        <latestAction>
          <actionDate>2019-09-23</actionDate>
          <text>Submitted in the Senate, considered, and agreed to without amendment and with a preamble by Unanimous Consent. (consideration: CR S5633; text: CR S5631-5632)</text>
        </latestAction>
        <relationshipDetails>
          <item>
            <type>Related bill</type>
            <identifiedBy>CRS</identifiedBy>
          </item>
        </relationshipDetails>
      </item>
      <item>
        <latestTitle>Expressing support for the designation of September 2020 as "National Kinship Care Month".</latestTitle>
        <congress>116</congress>
        <number>1101</number>
        <type>HRES</type>
        <latestAction>
          <actionDate>2020-09-11</actionDate>
          <text>Referred to the House Committee on Ways and Means.</text>
        </latestAction>
        <relationshipDetails>
          <item>
            <type>Identical bill</type>
            <identifiedBy>CRS</identifiedBy>
          </item>
        </relationshipDetails>
      </item>
      <item>
        <latestTitle>A resolution designating September 2020 as "National Kinship Care Month".</latestTitle>
        <congress>116</congress>
        <number>736</number>
        <type>SRES</type>
        <latestAction>
          <actionDate>2020-09-30</actionDate>
          <text>Submitted in the Senate, considered, and agreed to without amendment and with a preamble by Voice Vote. (consideration: CR S5998; text: CR S5985)</text>
        </latestAction>
        <relationshipDetails>
          <item>
            <type>Related bill</type>
            <identifiedBy>CRS</identifiedBy>
          </item>
        </relationshipDetails>
      </item>
    </relatedBills>
    <actions>
      <item>
        <actionDate>2019-08-27</actionDate>
        <committees>
          <item>
            <systemCode>hswm03</systemCode>
            <name>Worker and Family Support Subcommittee</name>
          </item>
        </committees>
        <links />
        <sourceSystem>
          <code>1</code>
          <name>House committee actions</name>
        </sourceSystem>
        <text>Referred to the Subcommittee on Worker and Family Support.</text>
        <type>Committee</type>
      </item>
      <item>
        <actionDate>2019-08-27</actionDate>
        <links />
        <text>Referred to the House Committee on Ways and Means.</text>
        <type>IntroReferral</type>
        <actionCode>H11100</actionCode>
        <sourceSystem>
          <code>2</code>
          <name>House floor actions</name>
        </sourceSystem>
        <committees>
          <item>
            <systemCode>hswm00</systemCode>
            <name>Ways and Means Committee</name>
          </item>
        </committees>
      </item>
      <item>
        <actionDate>2019-08-27</actionDate>
        <links />
        <text>Introduced in House</text>
        <type>IntroReferral</type>
        <actionCode>Intro-H</actionCode>
        <sourceSystem>
          <code>9</code>
          <name>Library of Congress</name>
        </sourceSystem>
        <committees />
      </item>
      <item>
        <actionDate>2019-08-27</actionDate>
        <links />
        <text>Introduced in House</text>
        <type>IntroReferral</type>
        <actionCode>1000</actionCode>
        <sourceSystem>
          <code>9</code>
          <name>Library of Congress</name>
        </sourceSystem>
        <committees />
      </item>
      <actionTypeCounts>
        <placeholderTextForH>1</placeholderTextForH>
        <billReferrals>1</billReferrals>
        <introducedInTheHouse>1</introducedInTheHouse>
        <introducedInHouse>1</introducedInHouse>
      </actionTypeCounts>
      <actionByCounts>
        <houseOfRepresentatives>4</houseOfRepresentatives>
      </actionByCounts>
    </actions>
    <sponsors>
      <item>
        <bioguideId>B001270</bioguideId>
        <fullName>Rep. Bass, Karen [D-CA-37]</fullName>
        <firstName>Karen</firstName>
        <middleName />
        <lastName>Bass</lastName>
        <party>D</party>
        <state>CA</state>
        <identifiers>
          <lisID>1996</lisID>
          <bioguideId>B001270</bioguideId>
          <gpoId>7838</gpoId>
        </identifiers>
        <district>37</district>
        <byRequestType />
      </item>
    </sponsors>
    <cosponsors>
      <item>
        <bioguideId>L000559</bioguideId>
        <fullName>Rep. Langevin, James R. [D-RI-2]</fullName>
        <firstName>JAMES</firstName>
        <middleName>R.</middleName>
        <lastName>LANGEVIN</lastName>
        <party>D</party>
        <state>RI</state>
        <identifiers>
          <lisID>1668</lisID>
          <bioguideId>L000559</bioguideId>
          <gpoId>8140</gpoId>
        </identifiers>
        <district>2</district>
        <sponsorshipDate>2019-09-17</sponsorshipDate>
        <isOriginalCosponsor>False</isOriginalCosponsor>
        <sponsorshipWithdrawnDate />
      </item>
      <item>
        <bioguideId>B001298</bioguideId>
        <fullName>Rep. Bacon, Don [R-NE-2]</fullName>
        <firstName>Don</firstName>
        <middleName />
        <lastName>Bacon</lastName>
        <party>R</party>
        <state>NE</state>
        <identifiers>
          <lisID>2337</lisID>
          <bioguideId>B001298</bioguideId>
          <gpoId />
        </identifiers>
        <district>2</district>
        <sponsorshipDate>2019-09-17</sponsorshipDate>
        <isOriginalCosponsor>False</isOriginalCosponsor>
        <sponsorshipWithdrawnDate />
      </item>
      <item>
        <bioguideId>L000581</bioguideId>
        <fullName>Rep. Lawrence, Brenda L. [D-MI-14]</fullName>
        <firstName>Brenda</firstName>
        <middleName>L.</middleName>
        <lastName>Lawrence</lastName>
        <party>D</party>
        <state>MI</state>
        <identifiers>
          <lisID>2252</lisID>
          <bioguideId>L000581</bioguideId>
          <gpoId />
        </identifiers>
        <district>14</district>
        <sponsorshipDate>2019-09-17</sponsorshipDate>
        <isOriginalCosponsor>False</isOriginalCosponsor>
        <sponsorshipWithdrawnDate />
      </item>
      <item>
        <bioguideId>M001201</bioguideId>
        <fullName>Rep. Mitchell, Paul [R-MI-10]</fullName>
        <firstName>Paul</firstName>
        <middleName />
        <lastName>Mitchell</lastName>
        <party>R</party>
        <state>MI</state>
        <identifiers>
          <lisID>2334</lisID>
          <bioguideId>M001201</bioguideId>
          <gpoId />
        </identifiers>
        <district>10</district>
        <sponsorshipDate>2019-09-17</sponsorshipDate>
        <isOriginalCosponsor>False</isOriginalCosponsor>
        <sponsorshipWithdrawnDate />
      </item>
      <item>
        <bioguideId>M001185</bioguideId>
        <fullName>Rep. Maloney, Sean Patrick [D-NY-18]</fullName>
        <firstName>Sean</firstName>
        <middleName>Patrick</middleName>
        <lastName>Maloney</lastName>
        <party>D</party>
        <state>NY</state>
        <identifiers>
          <lisID>2150</lisID>
          <bioguideId>M001185</bioguideId>
          <gpoId />
        </identifiers>
        <district>18</district>
        <sponsorshipDate>2019-09-17</sponsorshipDate>
        <isOriginalCosponsor>False</isOriginalCosponsor>
        <sponsorshipWithdrawnDate />
      </item>
      <item>
        <bioguideId>D000096</bioguideId>
        <fullName>Rep. Davis, Danny K. [D-IL-7]</fullName>
        <firstName>DANNY</firstName>
        <middleName>K.</middleName>
        <lastName>DAVIS</lastName>
        <party>D</party>
        <state>IL</state>
        <identifiers>
          <lisID>1477</lisID>
          <bioguideId>D000096</bioguideId>
          <gpoId>7927</gpoId>
        </identifiers>
        <district>7</district>
        <sponsorshipDate>2019-09-17</sponsorshipDate>
        <isOriginalCosponsor>False</isOriginalCosponsor>
        <sponsorshipWithdrawnDate />
      </item>
    </cosponsors>
    <cboCostEstimates />
    <laws />
    <notes />
    <policyArea>
      <name>Families</name>
    </policyArea>
    <subjects>
      <billSubjects>
        <legislativeSubjects>
          <item>
            <name>Adoption and foster care</name>
          </item>
          <item>
            <name>Child care and development</name>
          </item>
          <item>
            <name>Child safety and welfare</name>
          </item>
          <item>
            <name>Commemorative events and holidays</name>
          </item>
          <item>
            <name>Congressional tributes</name>
          </item>
          <item>
            <name>Family relationships</name>
          </item>
          <item>
            <name>Family services</name>
          </item>
        </legislativeSubjects>
        <policyArea>
          <name>Families</name>
        </policyArea>
      </billSubjects>
    </subjects>
    <summaries>
      <billSummaries>
        <item>
          <versionCode>00</versionCode>
          <actionDate>2019-08-27</actionDate>
          <actionDesc>Introduced in House</actionDesc>
          <lastSummaryUpdateDate>2020-09-30T16:20:18Z</lastSummaryUpdateDate>
          <text><![CDATA[<p>This resolution expresses support for the designation of National Kinship Care Month and encourages Congress to work to improve the lives of vulnerable children and families.</p>]]></text>
          <updateDate>2019-08-27T04:00:00Z</updateDate>
          <name>Introduced in House</name>
        </item>
      </billSummaries>
    </summaries>
    <title>Expressing support for the designation of September 2019 as "National Kinship Care Month".</title>
    <titles>
      <item>
        <titleType>Official Title as Introduced</titleType>
        <parentTitleType />
        <title>Expressing support for the designation of September 2019 as "National Kinship Care Month".</title>
        <chamberCode />
        <chamberName />
      </item>
      <item>
        <titleType>Display Title</titleType>
        <parentTitleType />
        <title>Expressing support for the designation of September 2019 as "National Kinship Care Month".</title>
        <chamberCode />
        <chamberName />
      </item>
    </titles>
    <amendments />
    <textVersions>
      <item>
        <type>Introduced in House</type>
        <date>2019-08-27T04:00:00Z</date>
        <formats>
          <item>
            <url>https://www.govinfo.gov/content/pkg/BILLS-116hres542ih/xml/BILLS-116hres542ih.xml</url>
          </item>
        </formats>
      </item>
    </textVersions>
    <latestAction>
      <actionDate>2019-08-27</actionDate>
      <text>Referred to the Subcommittee on Worker and Family Support.</text>
      <links />
    </latestAction>
    <calendarNumbers />
    <version>1.0.0</version>
  </bill>
  <dublinCore xmlns:dc="http://purl.org/dc/elements/1.1/">
    <dc:format>text/xml</dc:format>
    <dc:language>EN</dc:language>
    <dc:rights>Pursuant to Title 17 Section 105 of the United States Code, this file is not subject to copyright protection and is in the public domain.</dc:rights>
    <dc:contributor>Congressional Research Service, Library of Congress</dc:contributor>
    <dc:description>This file contains bill summaries and statuses for federal legislation. A bill summary describes the most significant provisions of a piece of legislation and details the effects the legislative text may have on current law and federal programs. Bill summaries are authored by the Congressional Research Service (CRS) of the Library of Congress. As stated in Public Law 91-510 (2 USC 166 (d)(6)), one of the duties of CRS is "to prepare summaries and digests of bills and resolutions of a public general nature introduced in the Senate or House of Representatives". For more information, refer to the User Guide that accompanies this file.</dc:description>
  </dublinCore>
</billStatus>

