{
  "actions": [
    {
      "acted_at": "2019-12-18", 
      "action_code": "Intro-H", 
      "references": [], 
      "text": "Introduced in House", 
      "type": "action"
    }, 
    {
      "acted_at": "2019-12-18", 
      "action_code": "H11100", 
      "committees": [
        "HSED"
      ], 
      "references": [], 
      "status": "REFERRED", 
      "text": "Referred to the Committee on Education and Labor, and in addition to the Committee on Ways and Means, for a period to be subsequently determined by the Speaker, in each case for consideration of such provisions as fall within the jurisdiction of the committee concerned.", 
      "type": "referral"
    }, 
    {
      "acted_at": "2019-12-18", 
      "action_code": "H11100", 
      "committees": [
        "HSWM"
      ], 
      "references": [], 
      "text": "Referred to the Committee on Education and Labor, and in addition to the Committee on Ways and Means, for a period to be subsequently determined by the Speaker, in each case for consideration of such provisions as fall within the jurisdiction of the committee concerned.", 
      "type": "referral"
    }
  ], 
  "amendments": [], 
  "bill_id": "hr5475-116", 
  "bill_type": "hr", 
  "by_request": false, 
  "committee_reports": [], 
  "committees": [
    {
      "activity": [
        "referral"
      ], 
      "committee": "House Ways and Means", 
      "committee_id": "HSWM"
    }, 
    {
      "activity": [
        "referral"
      ], 
      "committee": "House Education and Labor", 
      "committee_id": "HSED"
    }
  ], 
  "congress": "116", 
  "cosponsors": [
    {
      "bioguide_id": "E000179", 
      "district": "16", 
      "name": "Engel, Eliot L.", 
      "original_cosponsor": false, 
      "sponsored_at": "2020-02-27", 
      "state": "NY", 
      "title": "Rep", 
      "withdrawn_at": null
    }, 
    {
      "bioguide_id": "N000188", 
      "district": "1", 
      "name": "Norcross, Donald", 
      "original_cosponsor": true, 
      "sponsored_at": "2019-12-18", 
      "state": "NJ", 
      "title": "Rep", 
      "withdrawn_at": null
    }
  ], 
  "enacted_as": null, 
  "history": {
    "active": false, 
    "awaiting_signature": false, 
    "enacted": false, 
    "vetoed": false
  }, 
  "introduced_at": "2019-12-18", 
  "number": "5475", 
  "official_title": "To establish competitive Federal grants that will empower community colleges and minority-serving institutions to become incubators for infant and toddler child care talent, training, and access on their campuses and in their communities, and for other purposes.", 
  "popular_title": null, 
  "related_bills": [
    {
      "bill_id": "s3168-116", 
      "identified_by": "CRS", 
      "reason": "related", 
      "type": "bill"
    }
  ], 
  "short_title": "Preparing and Resourcing Our Student Parents and Early Childhood Teachers Act", 
  "sponsor": {
    "bioguide_id": "H001081", 
    "district": "5", 
    "name": "Hayes, Jahana", 
    "state": "CT", 
    "title": "Rep", 
    "type": "person"
  }, 
  "status": "REFERRED", 
  "status_at": "2019-12-18", 
  "subjects": [
    "Adult education and literacy", 
    "Child care and development", 
    "Congressional oversight", 
    "Disability and health-based discrimination", 
    "Disability and paralysis", 
    "Educational facilities and institutions", 
    "Elementary and secondary education", 
    "Employee hiring", 
    "Families", 
    "Family services", 
    "Foreign language and bilingual programs", 
    "Government information and archives", 
    "Higher education", 
    "Performance measurement", 
    "Racial and ethnic relations", 
    "Religion", 
    "Sex, gender, sexual orientation discrimination", 
    "State and local finance", 
    "Student aid and college costs", 
    "Teaching, teachers, curricula", 
    "User charges and fees", 
    "Wages and earnings"
  ], 
  "subjects_top_term": "Families", 
  "summary": null, 
  "titles": [
    {
      "as": null, 
      "is_for_portion": false, 
      "title": "PROSPECT Act", 
      "type": "display"
    }, 
    {
      "as": "introduced", 
      "is_for_portion": false, 
      "title": "Preparing and Resourcing Our Student Parents and Early Childhood Teachers Act", 
      "type": "short"
    }, 
    {
      "as": "introduced", 
      "is_for_portion": false, 
      "title": "Preparing and Resourcing Our Student Parents and Early Childhood Teachers Act", 
      "type": "short"
    }, 
    {
      "as": "introduced", 
      "is_for_portion": false, 
      "title": "PROSPECT Act", 
      "type": "short"
    }, 
    {
      "as": "introduced", 
      "is_for_portion": false, 
      "title": "PROSPECT Act", 
      "type": "short"
    }, 
    {
      "as": "introduced", 
      "is_for_portion": false, 
      "title": "To establish competitive Federal grants that will empower community colleges and minority-serving institutions to become incubators for infant and toddler child care talent, training, and access on their campuses and in their communities, and for other purposes.", 
      "type": "official"
    }
  ], 
  "updated_at": "2020-07-30T18:30:14Z", 
  "url": "https://www.govinfo.gov/bulkdata/BILLSTATUS/116/hr/BILLSTATUS-116hr5475.xml"
}